{
  "country": "MA",
  "city": "rabat",
  "source": "aladhan",
  "method": "other",
  "madhab": "shafi",
  "year": 2026,
  "month": 12,
  "timezone": "Africa/Casablanca",
  "coordinates": {
    "lat": 34.0209,
    "lon": -6.8416
  },
  "adjustments": {
    "maghrib": 5,
    "dhuhr": 5
  },
  "fajr_angle": 19.0,
  "isha_angle": 17.0,
  "days": [
    {
      "date": "2026-12-01",
      "fajr": "06:46",
      "sunrise": "08:14",
      "dhuhr": "13:16",
      "asr": "16:00",
      "maghrib": "18:18",
      "isha": "19:42"
    },
    {
      "date": "2026-12-02",
      "fajr": "06:47",
      "sunrise": "08:15",
      "dhuhr": "13:17",
      "asr": "16:00",
      "maghrib": "18:18",
      "isha": "19:42"
    },
    {
      "date": "2026-12-03",
      "fajr": "06:48",
      "sunrise": "08:16",
      "dhuhr": "13:17",
      "asr": "16:00",
      "maghrib": "18:18",
      "isha": "19:42"
    },
    {
      "date": "2026-12-04",
      "fajr": "06:48",
      "sunrise": "08:17",
      "dhuhr": "13:18",
      "asr": "16:00",
      "maghrib": "18:18",
      "isha": "19:42"
    },
    {
      "date": "2026-12-05",
      "fajr": "06:49",
      "sunrise": "08:18",
      "dhuhr": "13:18",
      "asr": "16:00",
      "maghrib": "18:18",
      "isha": "19:42"
    },
    {
      "date": "2026-12-06",
      "fajr": "06:50",
      "sunrise": "08:19",
      "dhuhr": "13:18",
      "asr": "16:00",
      "maghrib": "18:18",
      "isha": "19:42"
    },
    {
      "date": "2026-12-07",
      "fajr": "06:50",
      "sunrise": "08:19",
      "dhuhr": "13:19",
      "asr": "16:00",
      "maghrib": "18:18",
      "isha": "19:42"
    },
    {
      "date": "2026-12-08",
      "fajr": "06:51",
      "sunrise": "08:20",
      "dhuhr": "13:19",
      "asr": "16:00",
      "maghrib": "18:18",
      "isha": "19:42"
    },
    {
      "date": "2026-12-09",
      "fajr": "06:52",
      "sunrise": "08:21",
      "dhuhr": "13:20",
      "asr": "16:00",
      "maghrib": "18:18",
      "isha": "19:42"
    },
    {
      "date": "2026-12-10",
      "fajr": "06:53",
      "sunrise": "08:22",
      "dhuhr": "13:20",
      "asr": "16:00",
      "maghrib": "18:18",
      "isha": "19:43"
    },
    {
      "date": "2026-12-11",
      "fajr": "06:53",
      "sunrise": "08:23",
      "dhuhr": "13:21",
      "asr": "16:01",
      "maghrib": "18:19",
      "isha": "19:43"
    },
    {
      "date": "2026-12-12",
      "fajr": "06:54",
      "sunrise": "08:23",
      "dhuhr": "13:21",
      "asr": "16:01",
      "maghrib": "18:19",
      "isha": "19:43"
    },
    {
      "date": "2026-12-13",
      "fajr": "06:55",
      "sunrise": "08:24",
      "dhuhr": "13:22",
      "asr": "16:01",
      "maghrib": "18:19",
      "isha": "19:43"
    },
    {
      "date": "2026-12-14",
      "fajr": "06:55",
      "sunrise": "08:25",
      "dhuhr": "13:22",
      "asr": "16:01",
      "maghrib": "18:19",
      "isha": "19:44"
    },
    {
      "date": "2026-12-15",
      "fajr": "06:56",
      "sunrise": "08:25",
      "dhuhr": "13:22",
      "asr": "16:02",
      "maghrib": "18:20",
      "isha": "19:44"
    },
    {
      "date": "2026-12-16",
      "fajr": "06:56",
      "sunrise": "08:26",
      "dhuhr": "13:23",
      "asr": "16:02",
      "maghrib": "18:20",
      "isha": "19:44"
    },
    {
      "date": "2026-12-17",
      "fajr": "06:57",
      "sunrise": "08:27",
      "dhuhr": "13:23",
      "asr": "16:02",
      "maghrib": "18:20",
      "isha": "19:45"
    },
    {
      "date": "2026-12-18",
      "fajr": "06:58",
      "sunrise": "08:27",
      "dhuhr": "13:24",
      "asr": "16:03",
      "maghrib": "18:21",
      "isha": "19:45"
    },
    {
      "date": "2026-12-19",
      "fajr": "06:58",
      "sunrise": "08:28",
      "dhuhr": "13:24",
      "asr": "16:03",
      "maghrib": "18:21",
      "isha": "19:46"
    },
    {
      "date": "2026-12-20",
      "fajr": "06:59",
      "sunrise": "08:28",
      "dhuhr": "13:25",
      "asr": "16:04",
      "maghrib": "18:22",
      "isha": "19:46"
    },
    {
      "date": "2026-12-21",
      "fajr": "06:59",
      "sunrise": "08:29",
      "dhuhr": "13:25",
      "asr": "16:04",
      "maghrib": "18:22",
      "isha": "19:47"
    },
    {
      "date": "2026-12-22",
      "fajr": "07:00",
      "sunrise": "08:29",
      "dhuhr": "13:26",
      "asr": "16:05",
      "maghrib": "18:23",
      "isha": "19:47"
    },
    {
      "date": "2026-12-23",
      "fajr": "07:00",
      "sunrise": "08:30",
      "dhuhr": "13:26",
      "asr": "16:05",
      "maghrib": "18:23",
      "isha": "19:48"
    },
    {
      "date": "2026-12-24",
      "fajr": "07:01",
      "sunrise": "08:30",
      "dhuhr": "13:27",
      "asr": "16:06",
      "maghrib": "18:24",
      "isha": "19:48"
    },
    {
      "date": "2026-12-25",
      "fajr": "07:01",
      "sunrise": "08:31",
      "dhuhr": "13:27",
      "asr": "16:06",
      "maghrib": "18:24",
      "isha": "19:49"
    },
    {
      "date": "2026-12-26",
      "fajr": "07:01",
      "sunrise": "08:31",
      "dhuhr": "13:28",
      "asr": "16:07",
      "maghrib": "18:25",
      "isha": "19:49"
    },
    {
      "date": "2026-12-27",
      "fajr": "07:02",
      "sunrise": "08:31",
      "dhuhr": "13:28",
      "asr": "16:07",
      "maghrib": "18:25",
      "isha": "19:50"
    },
    {
      "date": "2026-12-28",
      "fajr": "07:02",
      "sunrise": "08:32",
      "dhuhr": "13:29",
      "asr": "16:08",
      "maghrib": "18:26",
      "isha": "19:51"
    },
    {
      "date": "2026-12-29",
      "fajr": "07:03",
      "sunrise": "08:32",
      "dhuhr": "13:29",
      "asr": "16:08",
      "maghrib": "18:27",
      "isha": "19:51"
    },
    {
      "date": "2026-12-30",
      "fajr": "07:03",
      "sunrise": "08:32",
      "dhuhr": "13:30",
      "asr": "16:09",
      "maghrib": "18:28",
      "isha": "19:52"
    },
    {
      "date": "2026-12-31",
      "fajr": "07:03",
      "sunrise": "08:33",
      "dhuhr": "13:30",
      "asr": "16:10",
      "maghrib": "18:28",
      "isha": "19:53"
    }
  ]
}