{
  "country": "MA",
  "city": "rabat",
  "source": "aladhan",
  "method": "other",
  "madhab": "shafi",
  "year": 2026,
  "month": 6,
  "timezone": "Africa/Casablanca",
  "coordinates": {
    "lat": 34.0209,
    "lon": -6.8416
  },
  "adjustments": {
    "maghrib": 5,
    "dhuhr": 5
  },
  "fajr_angle": 19.0,
  "isha_angle": 17.0,
  "days": [
    {
      "date": "2026-06-01",
      "fajr": "04:35",
      "sunrise": "06:17",
      "dhuhr": "13:25",
      "asr": "17:10",
      "maghrib": "20:34",
      "isha": "22:09"
    },
    {
      "date": "2026-06-02",
      "fajr": "04:35",
      "sunrise": "06:17",
      "dhuhr": "13:25",
      "asr": "17:10",
      "maghrib": "20:34",
      "isha": "22:10"
    },
    {
      "date": "2026-06-03",
      "fajr": "04:34",
      "sunrise": "06:17",
      "dhuhr": "13:26",
      "asr": "17:11",
      "maghrib": "20:35",
      "isha": "22:11"
    },
    {
      "date": "2026-06-04",
      "fajr": "04:34",
      "sunrise": "06:16",
      "dhuhr": "13:26",
      "asr": "17:11",
      "maghrib": "20:35",
      "isha": "22:11"
    },
    {
      "date": "2026-06-05",
      "fajr": "04:33",
      "sunrise": "06:16",
      "dhuhr": "13:26",
      "asr": "17:11",
      "maghrib": "20:36",
      "isha": "22:12"
    },
    {
      "date": "2026-06-06",
      "fajr": "04:33",
      "sunrise": "06:16",
      "dhuhr": "13:26",
      "asr": "17:11",
      "maghrib": "20:36",
      "isha": "22:13"
    },
    {
      "date": "2026-06-07",
      "fajr": "04:33",
      "sunrise": "06:16",
      "dhuhr": "13:26",
      "asr": "17:11",
      "maghrib": "20:37",
      "isha": "22:13"
    },
    {
      "date": "2026-06-08",
      "fajr": "04:32",
      "sunrise": "06:16",
      "dhuhr": "13:26",
      "asr": "17:12",
      "maghrib": "20:37",
      "isha": "22:14"
    },
    {
      "date": "2026-06-09",
      "fajr": "04:32",
      "sunrise": "06:16",
      "dhuhr": "13:27",
      "asr": "17:12",
      "maghrib": "20:38",
      "isha": "22:15"
    },
    {
      "date": "2026-06-10",
      "fajr": "04:32",
      "sunrise": "06:16",
      "dhuhr": "13:27",
      "asr": "17:12",
      "maghrib": "20:38",
      "isha": "22:15"
    },
    {
      "date": "2026-06-11",
      "fajr": "04:32",
      "sunrise": "06:16",
      "dhuhr": "13:27",
      "asr": "17:12",
      "maghrib": "20:39",
      "isha": "22:16"
    },
    {
      "date": "2026-06-12",
      "fajr": "04:31",
      "sunrise": "06:16",
      "dhuhr": "13:27",
      "asr": "17:12",
      "maghrib": "20:39",
      "isha": "22:16"
    },
    {
      "date": "2026-06-13",
      "fajr": "04:31",
      "sunrise": "06:16",
      "dhuhr": "13:27",
      "asr": "17:13",
      "maghrib": "20:40",
      "isha": "22:17"
    },
    {
      "date": "2026-06-14",
      "fajr": "04:31",
      "sunrise": "06:16",
      "dhuhr": "13:28",
      "asr": "17:13",
      "maghrib": "20:40",
      "isha": "22:17"
    },
    {
      "date": "2026-06-15",
      "fajr": "04:31",
      "sunrise": "06:16",
      "dhuhr": "13:28",
      "asr": "17:13",
      "maghrib": "20:40",
      "isha": "22:18"
    },
    {
      "date": "2026-06-16",
      "fajr": "04:31",
      "sunrise": "06:16",
      "dhuhr": "13:28",
      "asr": "17:13",
      "maghrib": "20:41",
      "isha": "22:18"
    },
    {
      "date": "2026-06-17",
      "fajr": "04:31",
      "sunrise": "06:16",
      "dhuhr": "13:28",
      "asr": "17:14",
      "maghrib": "20:41",
      "isha": "22:19"
    },
    {
      "date": "2026-06-18",
      "fajr": "04:31",
      "sunrise": "06:16",
      "dhuhr": "13:29",
      "asr": "17:14",
      "maghrib": "20:41",
      "isha": "22:19"
    },
    {
      "date": "2026-06-19",
      "fajr": "04:31",
      "sunrise": "06:16",
      "dhuhr": "13:29",
      "asr": "17:14",
      "maghrib": "20:41",
      "isha": "22:19"
    },
    {
      "date": "2026-06-20",
      "fajr": "04:32",
      "sunrise": "06:16",
      "dhuhr": "13:29",
      "asr": "17:14",
      "maghrib": "20:42",
      "isha": "22:19"
    },
    {
      "date": "2026-06-21",
      "fajr": "04:32",
      "sunrise": "06:16",
      "dhuhr": "13:29",
      "asr": "17:14",
      "maghrib": "20:42",
      "isha": "22:20"
    },
    {
      "date": "2026-06-22",
      "fajr": "04:32",
      "sunrise": "06:17",
      "dhuhr": "13:29",
      "asr": "17:15",
      "maghrib": "20:42",
      "isha": "22:20"
    },
    {
      "date": "2026-06-23",
      "fajr": "04:32",
      "sunrise": "06:17",
      "dhuhr": "13:30",
      "asr": "17:15",
      "maghrib": "20:42",
      "isha": "22:20"
    },
    {
      "date": "2026-06-24",
      "fajr": "04:33",
      "sunrise": "06:17",
      "dhuhr": "13:30",
      "asr": "17:15",
      "maghrib": "20:42",
      "isha": "22:20"
    },
    {
      "date": "2026-06-25",
      "fajr": "04:33",
      "sunrise": "06:18",
      "dhuhr": "13:30",
      "asr": "17:15",
      "maghrib": "20:43",
      "isha": "22:20"
    },
    {
      "date": "2026-06-26",
      "fajr": "04:33",
      "sunrise": "06:18",
      "dhuhr": "13:30",
      "asr": "17:16",
      "maghrib": "20:43",
      "isha": "22:20"
    },
    {
      "date": "2026-06-27",
      "fajr": "04:34",
      "sunrise": "06:18",
      "dhuhr": "13:30",
      "asr": "17:16",
      "maghrib": "20:43",
      "isha": "22:20"
    },
    {
      "date": "2026-06-28",
      "fajr": "04:34",
      "sunrise": "06:19",
      "dhuhr": "13:31",
      "asr": "17:16",
      "maghrib": "20:43",
      "isha": "22:20"
    },
    {
      "date": "2026-06-29",
      "fajr": "04:35",
      "sunrise": "06:19",
      "dhuhr": "13:31",
      "asr": "17:16",
      "maghrib": "20:43",
      "isha": "22:20"
    },
    {
      "date": "2026-06-30",
      "fajr": "04:35",
      "sunrise": "06:19",
      "dhuhr": "13:31",
      "asr": "17:16",
      "maghrib": "20:43",
      "isha": "22:20"
    }
  ]
}