{
  "country": "ID",
  "city": "surabaya",
  "source": "kemenag",
  "method": "singapore",
  "madhab": "shafi",
  "year": 2026,
  "month": 5,
  "timezone": "Asia/Jakarta",
  "coordinates": {
    "lat": -7.2575,
    "lon": 112.7521
  },
  "days": [
    {
      "date": "2026-05-01",
      "fajr": "04:11",
      "sunrise": "05:31",
      "dhuhr": "11:26",
      "asr": "14:48",
      "maghrib": "17:22",
      "isha": "18:33"
    },
    {
      "date": "2026-05-02",
      "fajr": "04:11",
      "sunrise": "05:31",
      "dhuhr": "11:26",
      "asr": "14:48",
      "maghrib": "17:21",
      "isha": "18:33"
    },
    {
      "date": "2026-05-03",
      "fajr": "04:11",
      "sunrise": "05:31",
      "dhuhr": "11:26",
      "asr": "14:48",
      "maghrib": "17:21",
      "isha": "18:33"
    },
    {
      "date": "2026-05-04",
      "fajr": "04:11",
      "sunrise": "05:31",
      "dhuhr": "11:26",
      "asr": "14:48",
      "maghrib": "17:21",
      "isha": "18:33"
    },
    {
      "date": "2026-05-05",
      "fajr": "04:11",
      "sunrise": "05:31",
      "dhuhr": "11:26",
      "asr": "14:48",
      "maghrib": "17:21",
      "isha": "18:32"
    },
    {
      "date": "2026-05-06",
      "fajr": "04:11",
      "sunrise": "05:31",
      "dhuhr": "11:26",
      "asr": "14:48",
      "maghrib": "17:20",
      "isha": "18:32"
    },
    {
      "date": "2026-05-07",
      "fajr": "04:11",
      "sunrise": "05:31",
      "dhuhr": "11:26",
      "asr": "14:48",
      "maghrib": "17:20",
      "isha": "18:32"
    },
    {
      "date": "2026-05-08",
      "fajr": "04:10",
      "sunrise": "05:31",
      "dhuhr": "11:26",
      "asr": "14:48",
      "maghrib": "17:20",
      "isha": "18:32"
    },
    {
      "date": "2026-05-09",
      "fajr": "04:10",
      "sunrise": "05:31",
      "dhuhr": "11:25",
      "asr": "14:48",
      "maghrib": "17:20",
      "isha": "18:32"
    },
    {
      "date": "2026-05-10",
      "fajr": "04:10",
      "sunrise": "05:31",
      "dhuhr": "11:25",
      "asr": "14:48",
      "maghrib": "17:20",
      "isha": "18:32"
    },
    {
      "date": "2026-05-11",
      "fajr": "04:10",
      "sunrise": "05:31",
      "dhuhr": "11:25",
      "asr": "14:48",
      "maghrib": "17:19",
      "isha": "18:32"
    },
    {
      "date": "2026-05-12",
      "fajr": "04:10",
      "sunrise": "05:31",
      "dhuhr": "11:25",
      "asr": "14:48",
      "maghrib": "17:19",
      "isha": "18:32"
    },
    {
      "date": "2026-05-13",
      "fajr": "04:10",
      "sunrise": "05:31",
      "dhuhr": "11:25",
      "asr": "14:48",
      "maghrib": "17:19",
      "isha": "18:32"
    },
    {
      "date": "2026-05-14",
      "fajr": "04:10",
      "sunrise": "05:32",
      "dhuhr": "11:25",
      "asr": "14:48",
      "maghrib": "17:19",
      "isha": "18:32"
    },
    {
      "date": "2026-05-15",
      "fajr": "04:10",
      "sunrise": "05:32",
      "dhuhr": "11:25",
      "asr": "14:48",
      "maghrib": "17:19",
      "isha": "18:32"
    },
    {
      "date": "2026-05-16",
      "fajr": "04:11",
      "sunrise": "05:32",
      "dhuhr": "11:25",
      "asr": "14:48",
      "maghrib": "17:19",
      "isha": "18:32"
    },
    {
      "date": "2026-05-17",
      "fajr": "04:11",
      "sunrise": "05:32",
      "dhuhr": "11:25",
      "asr": "14:48",
      "maghrib": "17:19",
      "isha": "18:32"
    },
    {
      "date": "2026-05-18",
      "fajr": "04:11",
      "sunrise": "05:32",
      "dhuhr": "11:25",
      "asr": "14:48",
      "maghrib": "17:19",
      "isha": "18:32"
    },
    {
      "date": "2026-05-19",
      "fajr": "04:11",
      "sunrise": "05:32",
      "dhuhr": "11:25",
      "asr": "14:48",
      "maghrib": "17:19",
      "isha": "18:32"
    },
    {
      "date": "2026-05-20",
      "fajr": "04:11",
      "sunrise": "05:33",
      "dhuhr": "11:26",
      "asr": "14:48",
      "maghrib": "17:18",
      "isha": "18:32"
    },
    {
      "date": "2026-05-21",
      "fajr": "04:11",
      "sunrise": "05:33",
      "dhuhr": "11:26",
      "asr": "14:48",
      "maghrib": "17:18",
      "isha": "18:32"
    },
    {
      "date": "2026-05-22",
      "fajr": "04:11",
      "sunrise": "05:33",
      "dhuhr": "11:26",
      "asr": "14:48",
      "maghrib": "17:18",
      "isha": "18:32"
    },
    {
      "date": "2026-05-23",
      "fajr": "04:11",
      "sunrise": "05:33",
      "dhuhr": "11:26",
      "asr": "14:48",
      "maghrib": "17:18",
      "isha": "18:32"
    },
    {
      "date": "2026-05-24",
      "fajr": "04:11",
      "sunrise": "05:33",
      "dhuhr": "11:26",
      "asr": "14:48",
      "maghrib": "17:18",
      "isha": "18:32"
    },
    {
      "date": "2026-05-25",
      "fajr": "04:11",
      "sunrise": "05:33",
      "dhuhr": "11:26",
      "asr": "14:48",
      "maghrib": "17:18",
      "isha": "18:32"
    },
    {
      "date": "2026-05-26",
      "fajr": "04:11",
      "sunrise": "05:34",
      "dhuhr": "11:26",
      "asr": "14:48",
      "maghrib": "17:18",
      "isha": "18:32"
    },
    {
      "date": "2026-05-27",
      "fajr": "04:11",
      "sunrise": "05:34",
      "dhuhr": "11:26",
      "asr": "14:48",
      "maghrib": "17:18",
      "isha": "18:32"
    },
    {
      "date": "2026-05-28",
      "fajr": "04:11",
      "sunrise": "05:34",
      "dhuhr": "11:26",
      "asr": "14:48",
      "maghrib": "17:18",
      "isha": "18:32"
    },
    {
      "date": "2026-05-29",
      "fajr": "04:12",
      "sunrise": "05:34",
      "dhuhr": "11:26",
      "asr": "14:48",
      "maghrib": "17:18",
      "isha": "18:33"
    },
    {
      "date": "2026-05-30",
      "fajr": "04:12",
      "sunrise": "05:35",
      "dhuhr": "11:27",
      "asr": "14:48",
      "maghrib": "17:18",
      "isha": "18:33"
    },
    {
      "date": "2026-05-31",
      "fajr": "04:12",
      "sunrise": "05:35",
      "dhuhr": "11:27",
      "asr": "14:48",
      "maghrib": "17:19",
      "isha": "18:33"
    }
  ]
}