{
  "country": "TR",
  "city": "manisa",
  "district": "manisa",
  "parent_city": "manisa",
  "source": "diyanet",
  "method": "turkey",
  "madhab": "shafi",
  "year": 2026,
  "month": 8,
  "timezone": "Europe/Istanbul",
  "adjustments": {
    "sunrise": -7,
    "dhuhr": 5,
    "asr": 4,
    "maghrib": 6,
    "isha": -1
  },
  "days": [
    {
      "date": "2026-08-01",
      "fajr": "04:26",
      "sunrise": "06:05",
      "dhuhr": "13:22",
      "asr": "17:12",
      "maghrib": "20:29",
      "isha": "22:00"
    },
    {
      "date": "2026-08-02",
      "fajr": "04:28",
      "sunrise": "06:06",
      "dhuhr": "13:22",
      "asr": "17:12",
      "maghrib": "20:28",
      "isha": "21:59"
    },
    {
      "date": "2026-08-03",
      "fajr": "04:29",
      "sunrise": "06:06",
      "dhuhr": "13:22",
      "asr": "17:12",
      "maghrib": "20:27",
      "isha": "21:57"
    }
  ]
}