{
  "country": "TR",
  "city": "ergene",
  "district": "ergene",
  "parent_city": "tekirdag",
  "source": "diyanet",
  "method": "turkey",
  "madhab": "shafi",
  "year": 2026,
  "month": 8,
  "timezone": "Europe/Istanbul",
  "adjustments": {
    "sunrise": -7,
    "dhuhr": 5,
    "asr": 4,
    "maghrib": 6,
    "isha": -1
  },
  "days": [
    {
      "date": "2026-08-01",
      "fajr": "04:12",
      "sunrise": "05:57",
      "dhuhr": "13:20",
      "asr": "17:15",
      "maghrib": "20:34",
      "isha": "22:11"
    },
    {
      "date": "2026-08-02",
      "fajr": "04:14",
      "sunrise": "05:58",
      "dhuhr": "13:20",
      "asr": "17:15",
      "maghrib": "20:33",
      "isha": "22:10"
    },
    {
      "date": "2026-08-03",
      "fajr": "04:15",
      "sunrise": "05:59",
      "dhuhr": "13:20",
      "asr": "17:14",
      "maghrib": "20:31",
      "isha": "22:08"
    },
    {
      "date": "2026-08-04",
      "fajr": "04:17",
      "sunrise": "06:00",
      "dhuhr": "13:20",
      "asr": "17:14",
      "maghrib": "20:30",
      "isha": "22:06"
    },
    {
      "date": "2026-08-05",
      "fajr": "04:18",
      "sunrise": "06:01",
      "dhuhr": "13:20",
      "asr": "17:13",
      "maghrib": "20:29",
      "isha": "22:05"
    }
  ]
}